termolab/__init__.py
termolab/plot_functions.py
termolab-0.0.1.dist-info/METADATA
termolab-0.0.1.dist-info/WHEEL
termolab-0.0.1.dist-info/licenses/LICENSE
termolab-0.0.1.dist-info/RECORD
