Metadata-Version: 2.1
Name: termolab
Version: 0.0.1
Summary: Paquete para poder analizar estados, procesos y ciclos termodinámicos.
Project-URL: Homepage, https://github.com/hermmanhender/termolabs
Project-URL: Bug Tracker, https://github.com/hermmanhender/termolabs/issues
Author: Germán Rodolfo Henderson
License-File: LICENSE
Classifier: License :: OSI Approved :: MIT License
Classifier: Operating System :: OS Independent
Classifier: Programming Language :: Python :: 3
Requires-Python: >=3.7
